setup.cfg
setup.py
pyfck/__init__.py
pyfck/getch.py
pyfck.egg-info/PKG-INFO
pyfck.egg-info/SOURCES.txt
pyfck.egg-info/dependency_links.txt
pyfck.egg-info/entry_points.txt
pyfck.egg-info/not-zip-safe
pyfck.egg-info/requires.txt
pyfck.egg-info/top_level.txt
pyfck/scripts/__init__.py
pyfck/scripts/cli.py