Metadata-Version: 1.1
Name: pyfck
Version: 0.1dev
Summary: A bare-bones Brainfuck interpreter written in Python 2.7. It's guaranteed to have bugs
Home-page: https://github.com/Deathnerd/pyfck
Author: Wes Gilleland
Author-email: wes.gilleland@gmail.com
License: MIT
Download-URL: https://github.com/Deathnerd/pyfck@master
Keywords: brainfuck interpreter command-line
Platform: UNKNOWN
